Metadata-Version: 1.1
Name: impstall
Version: 0.3.0
Summary: This module can be used to import python packages and install them if not already installed.
Home-page: https://github.com/ryanniehaus/impstall
Author: Ryan Niehaus
Author-email: impstall_dev@googlegroups.com
License: MIT
Keywords: import install package package management pypi development
Platform: UNKNOWN
Classifier: Development Status :: 3 - Alpha
Classifier: Intended Audience :: Developers
Classifier: Topic :: System :: Installation/Setup
Classifier: Topic :: System :: Software Distribution
Classifier: Topic :: Software Development :: Build Tools
Classifier: License :: OSI Approved :: MIT License
Classifier: Programming Language :: Python :: 2
Classifier: Programming Language :: Python :: 2.7
Classifier: Programming Language :: Python :: 3
Classifier: Programming Language :: Python :: 3.3
Classifier: Programming Language :: Python :: 3.4
Classifier: Programming Language :: Python :: 3.5
Provides: impstall
